certifiable/__init__.py
certifiable/__version__.py
certifiable/cli.py
certifiable/complex.py
certifiable/core.py
certifiable/errors.py
certifiable/operators.py
certifiable/utils.py
certifiable-0.1.dist-info/DESCRIPTION.rst
certifiable-0.1.dist-info/METADATA
certifiable-0.1.dist-info/RECORD
certifiable-0.1.dist-info/WHEEL
certifiable-0.1.dist-info/entry_points.txt
certifiable-0.1.dist-info/metadata.json
certifiable-0.1.dist-info/top_level.txt
