Metadata-Version: 2.0
Name: certifiable
Version: 0.1
Summary: Certifiers for everyone!
Home-page: https://github.com/sys-git/certifiable
Author: Francis Horsman
Author-email: francis.horsman@gmail.com
License: MIT license
Keywords: certifiable,validation
Platform: UNKNOWN
Classifier: Development Status :: 4 - Beta
Classifier: Intended Audience :: Developers
Classifier: License :: OSI Approved :: MIT License
Classifier: Natural Language :: English
Classifier: Programming Language :: Python :: 2
Classifier: Programming Language :: Python :: 2.7
Classifier: Programming Language :: Python :: 3
Classifier: Programming Language :: Python :: 3.5
Classifier: Programming Language :: Python :: 3.6
Classifier: Programming Language :: Python :: Implementation :: CPython
Classifier: Programming Language :: Python :: Implementation :: PyPy
Requires-Dist: email-validator (==1.0.3)
Requires-Dist: enum34 (==1.1.6)
Requires-Dist: lxml (==3.8.0)
Requires-Dist: six (==1.11.0)
